{
  "creationTime": 1579218515811,
  "expireTime": 1610792119557,
  "advisoryTimeFrame": "1 Week",
  "template": "Mainshock",
  "injectableText": "",
  "observations": [
    {
      "magnitude": 3.0,
      "count": 265
    },
    {
      "magnitude": 5.0,
      "count": 10
    },
    {
      "magnitude": 6.0,
      "count": 0
    },
    {
      "magnitude": 7.0,
      "count": 0
    }
  ],
  "model": {
    "name": "Epidemic-Type aftershock model (Bayesian Combination)",
    "reference": "#url",
    "parameters": {
      "ams": -1.48,
      "a": -2.25,
      "b": 1.0,
      "magMain": 6.4,
      "p": 0.95,
      "c": 0.0072,
      "Mc": 4.0
    }
  },
  "forecast": [
    {
      "timeStart": 1579219200647,
      "timeEnd": 1579305600647,
      "label": "1 Day",
      "bins": [
        {
          "magnitude": 3.0,
          "p95minimum": 2,
          "p95maximum": 35,
          "probability": 1.0
        },
        {
          "magnitude": 5.0,
          "p95minimum": 0,
          "p95maximum": 1,
          "probability": 0.1298
        },
        {
          "magnitude": 6.0,
          "p95minimum": 0,
          "p95maximum": 0,
          "probability": 0.0146
        },
        {
          "magnitude": 7.0,
          "p95minimum": 0,
          "p95maximum": 0,
          "probability": 0.0016
        }
      ],
      "aboveMainshockMag": {
        "magnitude": 6.4,
        "probability": 0.0063
      }
    },
    {
      "timeStart": 1579219200647,
      "timeEnd": 1579824000647,
      "label": "1 Week",
      "bins": [
        {
          "magnitude": 3.0,
          "p95minimum": 40,
          "p95maximum": 205,
          "probability": 1.0
        },
        {
          "magnitude": 5.0,
          "p95minimum": 0,
          "p95maximum": 4,
          "probability": 0.5387
        },
        {
          "magnitude": 6.0,
          "p95minimum": 0,
          "p95maximum": 1,
          "probability": 0.0796
        },
        {
          "magnitude": 7.0,
          "p95minimum": 0,
          "p95maximum": 0,
          "probability": 0.0092
        }
      ],
      "aboveMainshockMag": {
        "magnitude": 6.4,
        "probability": 0.0336
      }
    },
    {
      "timeStart": 1579219200647,
      "timeEnd": 1581897600647,
      "label": "1 Month",
      "bins": [
        {
          "magnitude": 3.0,
          "p95minimum": 125,
          "p95maximum": 778,
          "probability": 1.0
        },
        {
          "magnitude": 5.0,
          "p95minimum": 0,
          "p95maximum": 10,
          "probability": 0.8706
        },
        {
          "magnitude": 6.0,
          "p95minimum": 0,
          "p95maximum": 2,
          "probability": 0.2083
        },
        {
          "magnitude": 7.0,
          "p95minimum": 0,
          "p95maximum": 1,
          "probability": 0.0265
        }
      ],
      "aboveMainshockMag": {
        "magnitude": 6.4,
        "probability": 0.0938
      }
    },
    {
      "timeStart": 1579219200647,
      "timeEnd": 1610841600647,
      "label": "1 Year",
      "bins": [
        {
          "magnitude": 3.0,
          "p95minimum": 361,
          "p95maximum": 5701,
          "probability": 1.0
        },
        {
          "magnitude": 5.0,
          "p95minimum": 1,
          "p95maximum": 59,
          "probability": 0.9936
        },
        {
          "magnitude": 6.0,
          "p95minimum": 0,
          "p95maximum": 8,
          "probability": 0.5357
        },
        {
          "magnitude": 7.0,
          "p95minimum": 0,
          "p95maximum": 2,
          "probability": 0.0934
        }
      ],
      "aboveMainshockMag": {
        "magnitude": 6.4,
        "probability": 0.2857
      }
    }
  ]
}