{
  "creationTime": 1628290371513,
  "expireTime": 1659863975259,
  "advisoryTimeFrame": "1 Month",
  "template": "Mainshock",
  "injectableText": "",
  "observations": [
    {
      "magnitude": 3.0,
      "count": 1954
    },
    {
      "magnitude": 5.0,
      "count": 15
    },
    {
      "magnitude": 6.0,
      "count": 1
    },
    {
      "magnitude": 7.0,
      "count": 0
    }
  ],
  "model": {
    "name": "Epidemic-Type aftershock model (Bayesian Combination)",
    "reference": "#url",
    "parameters": {
      "ams": -1.73,
      "a": -2.03,
      "b": 1.15,
      "magMain": 6.4,
      "p": 0.99,
      "c": 0.0063,
      "Mc": 3.5
    }
  },
  "forecast": [
    {
      "timeStart": 1627776000000,
      "timeEnd": 1627862400000,
      "label": "1 Day",
      "bins": [
        {
          "magnitude": 3.0,
          "p95minimum": 0,
          "p95maximum": 2,
          "probability": 0.2637
        },
        {
          "magnitude": 4.0,
          "p95minimum": 0,
          "p95maximum": 0,
          "probability": 0.0228
        },
        {
          "magnitude": 5.0,
          "p95minimum": 0,
          "p95maximum": 0,
          "probability": 0.0017
        },
        {
          "magnitude": 6.0,
          "p95minimum": 0,
          "p95maximum": 0,
          "probability": 0.0001
        },
        {
          "magnitude": 7.0,
          "p95minimum": 0,
          "p95maximum": 0,
          "probability": 0.0
        }
      ],
      "aboveMainshockMag": {
        "magnitude": 6.4,
        "probability": 0.0
      }
    },
    {
      "timeStart": 1627776000000,
      "timeEnd": 1628380800000,
      "label": "1 Week",
      "bins": [
        {
          "magnitude": 3.0,
          "p95minimum": 0,
          "p95maximum": 9,
          "probability": 0.8571
        },
        {
          "magnitude": 4.0,
          "p95minimum": 0,
          "p95maximum": 2,
          "probability": 0.1424
        },
        {
          "magnitude": 5.0,
          "p95minimum": 0,
          "p95maximum": 0,
          "probability": 0.0116
        },
        {
          "magnitude": 6.0,
          "p95minimum": 0,
          "p95maximum": 0,
          "probability": 0.0012
        },
        {
          "magnitude": 7.0,
          "p95minimum": 0,
          "p95maximum": 0,
          "probability": 0.0
        }
      ],
      "aboveMainshockMag": {
        "magnitude": 6.4,
        "probability": 0.0003
      }
    },
    {
      "timeStart": 1627776000000,
      "timeEnd": 1630454400000,
      "label": "1 Month",
      "bins": [
        {
          "magnitude": 3.0,
          "p95minimum": 3,
          "p95maximum": 33,
          "probability": 0.9996
        },
        {
          "magnitude": 4.0,
          "p95minimum": 0,
          "p95maximum": 4,
          "probability": 0.4795
        },
        {
          "magnitude": 5.0,
          "p95minimum": 0,
          "p95maximum": 1,
          "probability": 0.0517
        },
        {
          "magnitude": 6.0,
          "p95minimum": 0,
          "p95maximum": 0,
          "probability": 0.0042
        },
        {
          "magnitude": 7.0,
          "p95minimum": 0,
          "p95maximum": 0,
          "probability": 0.0002
        }
      ],
      "aboveMainshockMag": {
        "magnitude": 6.4,
        "probability": 0.0011
      }
    },
    {
      "timeStart": 1627776000000,
      "timeEnd": 1659398400000,
      "label": "1 Year",
      "bins": [
        {
          "magnitude": 3.0,
          "p95minimum": 60,
          "p95maximum": 363,
          "probability": 1.0
        },
        {
          "magnitude": 4.0,
          "p95minimum": 2,
          "p95maximum": 29,
          "probability": 0.9951
        },
        {
          "magnitude": 5.0,
          "p95minimum": 0,
          "p95maximum": 4,
          "probability": 0.3768
        },
        {
          "magnitude": 6.0,
          "p95minimum": 0,
          "p95maximum": 1,
          "probability": 0.0378
        },
        {
          "magnitude": 7.0,
          "p95minimum": 0,
          "p95maximum": 0,
          "probability": 0.0028
        }
      ],
      "aboveMainshockMag": {
        "magnitude": 6.4,
        "probability": 0.0136
      }
    }
  ]
}